MANIFEST.in
README.rst
cleanweb.py
setup.py
cleanweb.egg-info/PKG-INFO
cleanweb.egg-info/SOURCES.txt
cleanweb.egg-info/dependency_links.txt
cleanweb.egg-info/requires.txt
cleanweb.egg-info/top_level.txt